Lab_3/Lab_3_1/comparator_4_bit.v
module comparator_4_bit(A, B, GA, EQU, GB);

	input [3:0] A;
	input [3:0] B;
	output GA, EQU, GB;
	reg GA, EQU, GB;
	//A to B

	always @(A or B)
	begin
		if($signed(A) > $signed(B))
			begin
				GA = 1;
				EQU = 0;
				GB = 0;
			end
		else if($signed(A) == $signed(B))
			begin
				GA = 0;
				EQU = 1;
				GB = 0;
			end
		else
			begin
				GA = 0;
				EQU = 0;
				GB = 1;
			end
		end

endmodule

Lab_3/Lab_3_1/test_bench.v
module test_bench;
	reg [3:0] A;
	reg [3:0] B;
	wire GA, EQU, GB;

	comparator_4_bit uut(.A(A), .B(B), .GA(GA), .EQU(EQU), .GB(GB));

	initial begin

		$dumpfile("test.vcd");
		$dumpvars(0, test_bench);
		//GA
		A = 4'b0110;
		B = 4'b1110;
		#100;
		A = 4'b0111;
		B = 4'b0100;
		#100;
		A = 4'b1111;
		B = 4'b1100;
		//EQU
		#100;
		A = 4'b1110;
		B = 4'b1110;
		#100;
		A = 4'b0110;
		B = 4'b0110;
		//GB
		#100;
		B = 4'b0110;
		A = 4'b1110;
		#100;
		B = 4'b0110;
		A = 4'b0100;
		#100;
		B = 4'b1111;
		A = 4'b1100;
		#100;
	end
	
endmodule

Lab_3/Lab_3_1/test.vcd
$date
	Sun Apr  5 11:32:03 2020
$end
$version
	Icarus Verilog
$end
$timescale
	1s
$end
$scope module test_bench $end
$var wire 1 ! GB $end
$var wire 1 " GA $end
$var wire 1 # EQU $end
$var reg 4 $ A [3:0] $end
$var reg 4 % B [3:0] $end
$scope module uut $end
$var wire 4 & A [3:0] $end
$var wire 4 ' B [3:0] $end
$var reg 1 # EQU $end
$var reg 1 " GA $end
$var reg 1 ! GB $end
$upscope $end
$upscope $end
$enddefinitions $end
#0
$dumpvars
b1110 '
b110 &
b1110 %
b110 $
0#
1"
0!
$end
#100
b100 %
b100 '
b111 $
b111 &
#200
b1100 %
b1100 '
b1111 $
b1111 &
#300
1#
0"
b1110 %
b1110 '
b1110 $
b1110 &
#400
b110 %
b110 '
b110 $
b110 &
#500
1!
0#
b1110 $
b1110 &
#600
b100 $
b100 &
#700
b1100 $
b1100 &
b1111 %
b1111 '
