Lab_3/Lab_3_2/fun.v
module fun(input [2:0] A, input [2:0] B, output C, D);

	assign C = (~B[1] & ~B[0] & ~A[2] & A[0]) | (~B[1] & ~A[2] & A[1]) | (~B[0] & ~A[2] & A[1] & A[0]) | (B[2] & ~A[2]) | (B[2] & ~B[1] & ~B[0] & A[0]) | (B[2] & ~B[1] & A[1]) | (B[2] & ~B[0] & A[1] & A[0]);
	assign D = (~B[2] & A[2]) | (~B[2] & B[0] & ~A[1] & ~A[0]) | (~B[2] & B[1] & ~A[1]) | (~B[2] & B[1] & B[0] & ~A[0]) | (B[0] & A[2] & ~A[1] & ~A[0]) | (B[1] & A[2] & ~A[1]) | (B[1] & B[0] & A[2] & ~A[0]);
endmodule

Lab_3/Lab_3_2/test.v
`timescale 1ns/100ps

module test;
	
	reg [2:0] A;
	reg [2:0] B;
	wire C,D;

	fun uut(.A(A), .B(B), .C(C), .D(D));

	initial begin

		$dumpfile("test.vcd");
		$dumpvars(0, test);
		//GA
		A = 3'b011;
		B = 3'b111;
		#100;
		A = 3'b011;
		B = 3'b010;
		#100;
		A = 3'b111;
		B = 3'b110;
		//EQU
		#100;
		A = 3'b111;
		B = 3'b111;
		#100;
		A = 3'b011;
		B = 3'b011;
		//GB
		#100;
		B = 3'b011;
		A = 3'b111;
		#100;
		B = 3'b011;
		A = 3'b010;
		#100;
		B = 3'b111;
		A = 3'b110;
		#100;
	end
endmodule

Lab_3/Lab_3_2/test.vcd
$date
	Sun Apr  5 13:39:30 2020
$end
$version
	Icarus Verilog
$end
$timescale
	100ps
$end
$scope module test $end
$var wire 1 ! D $end
$var wire 1 " C $end
$var reg 3 # A [2:0] $end
$var reg 3 $ B [2:0] $end
$scope module uut $end
$var wire 3 % A [2:0] $end
$var wire 3 & B [2:0] $end
$var wire 1 " C $end
$var wire 1 ! D $end
$upscope $end
$upscope $end
$enddefinitions $end
#0
$dumpvars
b111 &
b11 %
b111 $
b11 #
1"
0!
$end
#1000
1"
b10 $
b10 &
#2000
0!
b110 $
b110 &
b111 #
b111 %
#3000
0"
b111 $
b111 &
#4000
b11 $
b11 &
b11 #
b11 %
#5000
1!
b111 #
b111 %
#6000
b10 #
b10 %
#7000
0"
b110 #
b110 %
b111 $
b111 &
