Lab_2/lab_2_fun6.v
module lab_2_fun6(input [3:0] in, output F);
	wire A = in[3];
	wire B = in[2];
	wire C = in[1];
	wire D = in[0];

	assign F = (~C & D) | (~C & B);

endmodule

Lab_2/lab_2_fun2.v
module lab_2_fun2(input [3:0] in, output reg F);

	always @* begin
		case(in)
		default : F = 0;
		4'd5	: F = 1;
		4'd7	: F = 1;
		4'd12 : F = 1;
		4'd13 : F = 1;
		4'd15 : F = 1;
		endcase
	end

	

endmodule

Lab_2/lab_2_fun7.v
module lab_2_fun7(input A, B, C, D, output F);

	assign F = (~B & ~D) | (B & D) | (~B & C);

endmodule

Lab_2/lab_2_tb.v
`timescale 1ns/100ps

module lab_2_tb;
	
	wire A, B, C, D, F_2, F_6, F_7;
	wire [3:0] in_2;
	wire [3:0] in_6;
	integer i;
	assign {A, B, C, D} = i;
	assign in_2 = i;
	assign in_6 = i;
	lab_2_fun7 the_circut_7(A, B, C, D, F_7);
	lab_2_fun2 the_circut_2(in_2, F_2);
	lab_2_fun6 the_circut_6(in_6, F_6);

	initial begin

		$dumpfile("lab_2.vcd");
		$dumpvars(0, lab_2_tb);

		for(i = 4'd0; i<=4'd15; i=i+4'd1)
			#10 $display("done testing case %d",i);

		$finish;
	end
endmodule

Lab_2/lab_2.vcd
$date
	Sun Mar 29 22:55:36 2020
$end
$version
	Icarus Verilog
$end
$timescale
	100ps
$end
$scope module lab_2_tb $end
$var wire 4 ! in_6 [3:0] $end
$var wire 4 " in_2 [3:0] $end
$var wire 1 # F_7 $end
$var wire 1 $ F_6 $end
$var wire 1 % F_2 $end
$var wire 1 & D $end
$var wire 1 ' C $end
$var wire 1 ( B $end
$var wire 1 ) A $end
$var integer 32 * i [31:0] $end
$scope module the_circut_2 $end
$var wire 4 + in [3:0] $end
$var reg 1 % F $end
$upscope $end
$scope module the_circut_6 $end
$var wire 1 $ F $end
$var wire 4 , in [3:0] $end
$var wire 1 - D $end
$var wire 1 . C $end
$var wire 1 / B $end
$var wire 1 0 A $end
$upscope $end
$scope module the_circut_7 $end
$var wire 1 ) A $end
$var wire 1 ( B $end
$var wire 1 ' C $end
$var wire 1 & D $end
$var wire 1 # F $end
$upscope $end
$upscope $end
$enddefinitions $end
#0
$dumpvars
00
0/
0.
0-
b0 ,
b0 +
b0 *
0)
0(
0'
0&
0%
0$
1#
b0 "
b0 !
$end
#100
0#
1$
1&
1-
b1 "
b1 +
b1 !
b1 ,
b1 *
#200
1#
0$
0&
1'
1.
0-
b10 "
b10 +
b10 !
b10 ,
b10 *
#300
1&
1-
b11 "
b11 +
b11 !
b11 ,
b11 *
#400
0#
1$
0&
0'
1(
1/
0.
0-
b100 "
b100 +
b100 !
b100 ,
b100 *
#500
1#
1&
1%
1-
b101 "
b101 +
b101 !
b101 ,
b101 *
#600
0#
0$
0&
1'
0%
1.
0-
b110 "
b110 +
b110 !
b110 ,
b110 *
#700
1#
1&
1%
1-
b111 "
b111 +
b111 !
b111 ,
b111 *
#800
1#
0&
0'
0(
1)
0%
10
0/
0.
0-
b1000 "
b1000 +
b1000 !
b1000 ,
b1000 *
#900
0#
1$
1&
1-
b1001 "
b1001 +
b1001 !
b1001 ,
b1001 *
#1000
1#
0$
0&
1'
1.
0-
b1010 "
b1010 +
b1010 !
b1010 ,
b1010 *
#1100
1&
1-
b1011 "
b1011 +
b1011 !
b1011 ,
b1011 *
#1200
0#
1$
0&
0'
1(
1%
1/
0.
0-
b1100 "
b1100 +
b1100 !
b1100 ,
b1100 *
#1300
1#
1&
1-
b1101 "
b1101 +
b1101 !
b1101 ,
b1101 *
#1400
0#
0$
0&
1'
0%
1.
0-
b1110 "
b1110 +
b1110 !
b1110 ,
b1110 *
#1500
1#
1&
1%
1-
b1111 "
b1111 +
b1111 !
b1111 ,
b1111 *
#1600
1#
0&
0'
0(
0)
0%
00
0/
0.
0-
b0 "
b0 +
b0 !
b0 ,
b10000 *
