Projekt/counter.v
module counter(clk, reset, ctrl, out);

	parameter N = 4;	//Parametr. Domyślnie 4 bit out, N >= 2
	input clk, reset;	//Zegar oraz reset
	input [1:0] ctrl;	//Sterowanie 2-bitowe
	output [N-1:0] out;	//Wyjście N-bitowe, kod Gray'a
	reg [N-1:0] tmp;	//Zmienna pomocnicza, kod binarny

	always @(posedge clk, negedge reset) begin
		//Sprawdzenie resetu
		if (reset == 0) begin	
			tmp <= 0;
		end else begin
				//Sterowanie na licznik do tyłu
				if (ctrl == 0) begin
					tmp <= tmp - 1;
				//Sterowanie na licznik sterowany ctrl w kodzie U2
				end else begin
					//Użycie modyfikatora $signed umożliwia działania na liczbach w kodzie U2
					tmp <= $signed(tmp) + $signed(ctrl);
				end
		end
	end
	//Konwersja z N-bitowego kodu binarnego na N-bitowy kod Gray'a
	assign out = {tmp[N-1], tmp[N-1:1] ^ tmp[N-2:0]}; // ^ - operator XOR
endmodule

Projekt/test_bench.v
`timescale 1ns/100ps

module test_bench;

	parameter N = 4;	//Parametr. Domyślnie 4 bit out, N >= 2
	//Input
	reg clk = 0;		//Zegar
	reg reset;			//Reset
	reg [1:0] ctrl = 0;	//Sterowanie 2-bitowe

	//Output
	wire [N-1:0] out;	//Wyjście N-bitowe

	always 
		# 10 clk = ~clk;	//Zmiana zegara, okres 20 ns

		counter count(clk, reset, ctrl, out);	//Wywołanie modułu counter

	initial begin

		$dumpfile("counter.vcd");
		$dumpvars(0, test_bench);

		reset = 0;
		#5 reset = 1;		//Ustawienie resetu
		#150 ctrl = 2'b01;
		#150 ctrl = 2'b11;
		#150 $finish;
	end

endmodule

Projekt/counter.vcd
$date
	Fri Apr 24 23:18:40 2020
$end
$version
	Icarus Verilog
$end
$timescale
	100ps
$end
$scope module test_bench $end
$var wire 5 ! out [4:0] $end
$var reg 1 " clk $end
$var reg 2 # ctrl [1:0] $end
$var reg 1 $ reset $end
$scope module count $end
$var wire 1 " clk $end
$var wire 2 % ctrl [1:0] $end
$var wire 1 $ reset $end
$var wire 5 & out [4:0] $end
$var reg 5 ' tmp [4:0] $end
$upscope $end
$upscope $end
$enddefinitions $end
#0
$dumpvars
b0 '
b0 &
b0 %
0$
b0 #
0"
b0 !
$end
#50
1$
#100
b10000 !
b10000 &
b11111 '
1"
#200
0"
#300
b10001 !
b10001 &
b11110 '
1"
#400
0"
#500
b10011 !
b10011 &
b11101 '
1"
#600
0"
#700
b10010 !
b10010 &
b11100 '
1"
#800
0"
#900
b10110 !
b10110 &
b11011 '
1"
#1000
0"
#1100
b10111 !
b10111 &
b11010 '
1"
#1200
0"
#1300
b10101 !
b10101 &
b11001 '
1"
#1400
0"
#1500
b10100 !
b10100 &
b11000 '
1"
#1550
b1 #
b1 %
#1600
0"
#1700
b10101 !
b10101 &
b11001 '
1"
#1800
0"
#1900
b10111 !
b10111 &
b11010 '
1"
#2000
0"
#2100
b10110 !
b10110 &
b11011 '
1"
#2200
0"
#2300
b10010 !
b10010 &
b11100 '
1"
#2400
0"
#2500
b10011 !
b10011 &
b11101 '
1"
#2600
0"
#2700
b10001 !
b10001 &
b11110 '
1"
#2800
0"
#2900
b10000 !
b10000 &
b11111 '
1"
#3000
0"
#3050
b11 #
b11 %
#3100
b10001 !
b10001 &
b11110 '
1"
#3200
0"
#3300
b10011 !
b10011 &
b11101 '
1"
#3400
0"
#3500
b10010 !
b10010 &
b11100 '
1"
#3600
0"
#3700
b10110 !
b10110 &
b11011 '
1"
#3800
0"
#3900
b10111 !
b10111 &
b11010 '
1"
#4000
0"
#4100
b10101 !
b10101 &
b11001 '
1"
#4200
0"
#4300
b10100 !
b10100 &
b11000 '
1"
#4400
0"
#4500
b11100 !
b11100 &
b10111 '
1"
